mdfy/__init__.py
mdfy/mdfy.py
mdfy/py.typed
mdfy/shorthand.py
mdfy/types.py
mdfy/utils.py
mdfy/elements/__init__.py
mdfy/elements/_base.py
mdfy/elements/code.py
mdfy/elements/header.py
mdfy/elements/horizontal.py
mdfy/elements/image.py
mdfy/elements/link.py
mdfy/elements/list.py
mdfy/elements/quote.py
mdfy/elements/table.py
mdfy/elements/text.py
mdfy/elements/text_formatter.py
mdfy/elements/toc.py
mdfy/elements/formatter/lark_formatter.py
mdfy-0.10.0.dist-info/METADATA
mdfy-0.10.0.dist-info/WHEEL
mdfy-0.10.0.dist-info/top_level.txt
mdfy-0.10.0.dist-info/RECORD
