Metadata-Version: 2.4
Name: mdfy
Version: 0.10.0
Summary: Transform text into beautiful markdown, effortlessly.
Author-email: k-ush <argoooooon@gmail.com>
Project-URL: homepage, https://github.com/argonism/mdfy
Project-URL: repository, https://github.com/argonism/mdfy
Classifier: Typing :: Typed
Requires-Python: <4.0,>=3.9
Provides-Extra: styled-text
Requires-Dist: lark>=1.2.2; extra == "styled-text"
Provides-Extra: dev
Requires-Dist: ruff>=0.0.1111; extra == "dev"
Requires-Dist: pytest>=7.4.2; extra == "dev"
Requires-Dist: mypy>=1.5.1; extra == "dev"
Requires-Dist: black>=23.9.1; extra == "dev"
Requires-Dist: tox>=4.8.0; extra == "dev"
Requires-Dist: tox-gh-actions>=3.1.3; extra == "dev"
Requires-Dist: xdoctest>=1.2.0; extra == "dev"
Provides-Extra: docs
Requires-Dist: sphinx>=7.1.2; extra == "docs"
Requires-Dist: furo>=2023.9.10; extra == "docs"
Requires-Dist: sphinx-copybutton>=0.5.2; extra == "docs"
Requires-Dist: sphinx-design>=0.5.0; extra == "docs"
Requires-Dist: sphinx-autobuild>=2021.3.14; extra == "docs"
Requires-Dist: myst-parser>=2.0.0; extra == "docs"
Requires-Dist: sphinx-multiversion>=0.2.4; extra == "docs"
